{"data":{"Year":[2014,2016,2017,2018,2019,2020,2021,2022,2017,2018,2019,2020,2021,2022,2017,2018,2019,2020,2021,2022,2022],"Source details":["Nairobi City County","Nairobi City County","Nairobi City County","Nairobi City County","Nairobi City County","Nairobi City County","Nairobi City County","Nairobi City County","Mombasa County","Mombasa County","Mombasa County","Mombasa County","Mombasa County","Mombasa County","Kisumu County","Kisumu County","Kisumu County","Kisumu County","Kisumu County","Kisumu County","Nakuru Coutny"],"Reference area":["Nairobi City","Nairobi City","Nairobi City","Nairobi City","Nairobi City","Nairobi City","Nairobi City","Nairobi City","Mombasa city","Mombasa city","Mombasa city","Mombasa city","Mombasa city","Mombasa city","Kisumu City","Kisumu City","Kisumu City","Kisumu City","Kisumu City","Kisumu City","Nakuru City"],"Value":[44.0,56.6,53.6,57.4,75.2,75.2,76.7,77.4,25.1,56.0,46.1,46.0,56.5,65.0,30.0,30.0,30.0,30.0,30.0,30.1,60.0]},"edges":{"From":["Source details"],"To":["Reference area"]}}